string_scanner-0.0.1.dist-info/DESCRIPTION.rst
string_scanner-0.0.1.dist-info/METADATA
string_scanner-0.0.1.dist-info/RECORD
string_scanner-0.0.1.dist-info/WHEEL
string_scanner-0.0.1.dist-info/metadata.json
string_scanner-0.0.1.dist-info/top_level.txt
strscan/__init__.py
strscan/string_scanner.py
